c_four_five_classifier/__init__.py
c_four_five_classifier/c45.py
c_four_five_classifier-0.1.0.dist-info/METADATA
c_four_five_classifier-0.1.0.dist-info/WHEEL
c_four_five_classifier-0.1.0.dist-info/top_level.txt
c_four_five_classifier-0.1.0.dist-info/RECORD
